lambda_toolkit/__init__.py
lambda_toolkit/data/lambda-toolkit.json
lambda_toolkit/data/helps/cli.txt
lambda_toolkit/data/helps/invoke.txt
lambda_toolkit/data/helps/list.txt
lambda_toolkit/data/helps/project.txt
lambda_toolkit/data/helps/proxy.txt
lambda_toolkit/data/helps/queue.txt
lambda_toolkit/data/helps/receiver.txt
lambda_toolkit/data/helps/role.txt
lambda_toolkit/data/lambda-proxy/index.js
lambda_toolkit/data/lambda-proxy/index.py
lambda_toolkit/data/standard-folder/invoke/contexts/js.json
lambda_toolkit/data/standard-folder/invoke/contexts/python.json
lambda_toolkit/data/standard-folder/invoke/events/cloudformation.json
lambda_toolkit/data/standard-folder/invoke/events/cloudwatch_events.json
lambda_toolkit/data/standard-folder/invoke/events/cloudwatch_logs.json
lambda_toolkit/data/standard-folder/invoke/events/codepipeline.json
lambda_toolkit/data/standard-folder/invoke/events/cognito_sync_trigger.json
lambda_toolkit/data/standard-folder/invoke/events/config_rule.json
lambda_toolkit/data/standard-folder/invoke/events/dynamodb_update.json
lambda_toolkit/data/standard-folder/invoke/events/helloworld.json
lambda_toolkit/data/standard-folder/invoke/events/kinesis_stream.json
lambda_toolkit/data/standard-folder/invoke/events/s3_delete.json
lambda_toolkit/data/standard-folder/invoke/events/s3_put.json
lambda_toolkit/data/standard-folder/invoke/events/scheduled.json
lambda_toolkit/data/standard-folder/invoke/events/ses.json
lambda_toolkit/data/standard-folder/invoke/events/sns.json
lambda_toolkit/data/standard-folder/lambdas/README.txt
lambda_toolkit/data/standard-lambda/index.js
lambda_toolkit/data/standard-lambda/index.py
lambda_toolkit/modules/__init__.py
lambda_toolkit/modules/cli.py
lambda_toolkit/modules/conf.py
lambda_toolkit/modules/invoke.py
lambda_toolkit/modules/lambdacontext.py
lambda_toolkit/modules/logger.py
lambda_toolkit/modules/project.py
lambda_toolkit/modules/proxy.py
lambda_toolkit/modules/queue.py
lambda_toolkit-0.3.7.dist-info/DESCRIPTION.rst
lambda_toolkit-0.3.7.dist-info/METADATA
lambda_toolkit-0.3.7.dist-info/RECORD
lambda_toolkit-0.3.7.dist-info/WHEEL
lambda_toolkit-0.3.7.dist-info/metadata.json
lambda_toolkit-0.3.7.dist-info/top_level.txt
