Metadata-Version: 2.0
Name: lambda-toolkit
Version: 0.3.7
Summary: An AWS Lambda command line interface (CLI). It helps you in creating, building, testing and deploying your lambda functions.
Home-page: https://github.com/lucioveloso/lambda-toolkit
Author: Lucio Veloso Guimaraes
Author-email: lucio.veloso@gmail.com
License: UNKNOWN
Platform: UNKNOWN
Classifier: Development Status :: 4 - Beta
Classifier: Intended Audience :: Developers
Classifier: Intended Audience :: System Administrators
Classifier: Natural Language :: English
Classifier: License :: OSI Approved :: Apache Software License
Classifier: Programming Language :: Python
Classifier: Programming Language :: Python :: 2
Classifier: Programming Language :: Python :: 3
Requires-Dist: boto3 (>=1.4.4)
Requires-Dist: botocore (>=1.5.78)
Requires-Dist: click (>=6.7.0)
Requires-Dist: tail-toolkit (>=0.0.7)
